blag/__init__.py
blag/blag.py
blag/devserver.py
blag/markdown.py
blag/quickstart.py
blag/version.py
blag/content/about.md
blag/content/hello-world.md
blag/content/second-post.md
blag/content/testpage.md
blag/static/blag.png
blag/static/code-dark.css
blag/static/code-light.css
blag/static/favicon.ico
blag/static/style.css
blag/templates/archive.html
blag/templates/article.html
blag/templates/base.html
blag/templates/index.html
blag/templates/page.html
blag/templates/tag.html
blag/templates/tags.html
blag-2.3.3.dist-info/licenses/LICENSE
tests/__init__.py
tests/conftest.py
tests/test_blag.py
tests/test_devserver.py
tests/test_markdown.py
tests/test_quickstart.py
tests/test_templates.py
tests/test_version.py
blag-2.3.3.dist-info/METADATA
blag-2.3.3.dist-info/WHEEL
blag-2.3.3.dist-info/entry_points.txt
blag-2.3.3.dist-info/top_level.txt
blag-2.3.3.dist-info/RECORD
