Metadata-Version: 2.4
Name: blag
Version: 2.3.3
Summary: blog-aware, static site generator
Author-email: Bastian Venthur <mail@venthur.de>
Project-URL: Documentation, https://blag.readthedocs.io/
Project-URL: Source, https://github.com/venthur/blag
Project-URL: Changelog, https://github.com/venthur/blag/blob/master/CHANGELOG.md
Keywords: markdown,blag,blog,static site generator,cli
Requires-Python: >=3.10
License-File: LICENSE
Requires-Dist: feedgenerator
Requires-Dist: jinja2
Requires-Dist: markdown
Requires-Dist: pygments
Provides-Extra: dev
Requires-Dist: build; extra == "dev"
Requires-Dist: mkdocs; extra == "dev"
Requires-Dist: mkdocs-material; extra == "dev"
Requires-Dist: mkdocstrings[python]; extra == "dev"
Requires-Dist: mypy; extra == "dev"
Requires-Dist: pip-tools; extra == "dev"
Requires-Dist: pytest; extra == "dev"
Requires-Dist: pytest-cov; extra == "dev"
Requires-Dist: ruff; extra == "dev"
Requires-Dist: twine; extra == "dev"
Requires-Dist: types-markdown; extra == "dev"
Requires-Dist: wheel; extra == "dev"
Dynamic: license-file
